django_object_lock/__init__.py
django_object_lock/apps.py
django_object_lock/exceptions.py
django_object_lock/mixins.py
django_object_lock/models.py
django_object_lock/settings.py
django_object_lock/admin/__init__.py
django_object_lock/admin/views.py
django_object_lock/api/__init__.py
django_object_lock/api/exceptions.py
django_object_lock/api/mixins.py
django_object_lock/migrations/__init__.py
django_object_lock/static/django_object_lock/css/admin.css
django_object_lock/static/django_object_lock/images/locked.svg
django_object_lock/templates/django_object_lock/admin_lock.html
django_object_lock/templates/django_object_lock/admin_unlock.html
django_object_lock-1.0.0.dist-info/LICENSE
django_object_lock-1.0.0.dist-info/METADATA
django_object_lock-1.0.0.dist-info/WHEEL
django_object_lock-1.0.0.dist-info/top_level.txt
django_object_lock-1.0.0.dist-info/RECORD
