Metadata-Version: 2.1
Name: django-object-lock
Version: 1.0.0
Summary: Lock your model instances to prevent their unintended modification or deletion.
Author-email: Daikoderu <daikoderu@gmail.com>
License: MIT License
Project-URL: Homepage, https://github.com/daikoderu/django-object-lock
Classifier: Programming Language :: Python :: 3
Classifier: Natural Language :: English
Classifier: License :: OSI Approved :: MIT License
Classifier: Operating System :: OS Independent
Requires-Python: >=3.8
License-File: LICENSE
Requires-Dist: django
